qlog/__init__.py
qlog/logger.py
qlog/trace.py
qlog/utils.py
qlog/test/__init__.py
qlog/test/handlertest.py
log.client-1.0.0.dist-info/METADATA
log.client-1.0.0.dist-info/WHEEL
log.client-1.0.0.dist-info/top_level.txt
log.client-1.0.0.dist-info/RECORD
